odoo/addons/account_invoice_refund_reinvoice/README.rst
odoo/addons/account_invoice_refund_reinvoice/__init__.py
odoo/addons/account_invoice_refund_reinvoice/__manifest__.py
odoo/addons/account_invoice_refund_reinvoice/i18n/account_invoice_refund_reinvoice.pot
odoo/addons/account_invoice_refund_reinvoice/models/__init__.py
odoo/addons/account_invoice_refund_reinvoice/models/account_move.py
odoo/addons/account_invoice_refund_reinvoice/readme/CONTRIBUTORS.rst
odoo/addons/account_invoice_refund_reinvoice/readme/DESCRIPTION.rst
odoo/addons/account_invoice_refund_reinvoice/readme/USAGE.rst
odoo/addons/account_invoice_refund_reinvoice/static/description/icon.png
odoo/addons/account_invoice_refund_reinvoice/static/description/index.html
odoo/addons/account_invoice_refund_reinvoice/tests/__init__.py
odoo/addons/account_invoice_refund_reinvoice/tests/test_refund_invoice.py
odoo/addons/account_invoice_refund_reinvoice/views/account_move.xml
odoo13_addon_account_invoice_refund_reinvoice-13.0.1.0.1.dev3.dist-info/METADATA
odoo13_addon_account_invoice_refund_reinvoice-13.0.1.0.1.dev3.dist-info/WHEEL
odoo13_addon_account_invoice_refund_reinvoice-13.0.1.0.1.dev3.dist-info/top_level.txt
odoo13_addon_account_invoice_refund_reinvoice-13.0.1.0.1.dev3.dist-info/RECORD
